README.md
setup.py
co6co.web_session.egg-info/PKG-INFO
co6co.web_session.egg-info/SOURCES.txt
co6co.web_session.egg-info/dependency_links.txt
co6co.web_session.egg-info/requires.txt
co6co.web_session.egg-info/top_level.txt
co6co.web_session.egg-info/zip-safe
co6co_web_session/__init__.py
co6co_web_session/aioredis.py
co6co_web_session/base.py
co6co_web_session/memcache.py
co6co_web_session/memory.py
co6co_web_session/mongodb.py
co6co_web_session/redis.py
co6co_web_session/session.py
co6co_web_session/utils.py
co6co_web_session/versions.py